CFNCFSP/__init__.py
CFNCFSP/data/RoleIdentification_dict.py
CFNCFSP/data/WordSpliting_dicts.py
CFNCFSP/data/__init__.py
CFNCFSP/data/all_targets.bin
CFNCFSP/model/__init__.py
CFNCFSP/model/base.py
CFNCFSP/model/ArgumentIdentification/__init__.py
CFNCFSP/model/ArgumentIdentification/model.py
CFNCFSP/model/FrameIdentification/__init__.py
CFNCFSP/model/FrameIdentification/model.py
CFNCFSP/model/RoleIdentification/__init__.py
CFNCFSP/model/RoleIdentification/model.py
CFNCFSP/model/WordSplitting/__init__.py
CFNCFSP/model/WordSplitting/model.py
CFNCFSP/parser/__init__.py
CFNCFSP/parser/parser.py
CFNCFSP/schema/__init__.py
CFNCFSP/schema/base.py
CFNCFSP/schema/frame.py
CFNCFSP/utils/__init__.py
CFNCFSP/utils/cfn_cache.py
CFNCFSP/utils/get_dimensions.py
CFNCFSP-1.1.dist-info/METADATA
CFNCFSP-1.1.dist-info/WHEEL
CFNCFSP-1.1.dist-info/top_level.txt
CFNCFSP-1.1.dist-info/RECORD
