Metadata-Version: 2.1
Name: CFNCFSP
Version: 1.1
Summary: Empower your workflow with our toolkit: Word Segmentation with target word search, Frame Identification, Argument Identification and Role Identification. Chain these functions in a flexible pipeline, allowing users to search for all target words or specify their own, delivering tailored results.
Author: 
Author-email: 
Requires-Dist: pydantic ==2.4.2
Requires-Dist: torch ==1.13.1
Requires-Dist: transformers ==4.24.0
Requires-Dist: ltp ==4.2.13
